inspire_schemas/__init__.py
inspire_schemas/api.py
inspire_schemas/errors.py
inspire_schemas/utils.py
inspire_schemas/builders/__init__.py
inspire_schemas/builders/authors.py
inspire_schemas/builders/builder.py
inspire_schemas/builders/conferences.py
inspire_schemas/builders/data.py
inspire_schemas/builders/jobs.py
inspire_schemas/builders/literature.py
inspire_schemas/builders/references.py
inspire_schemas/builders/seminars.py
inspire_schemas/builders/signatures.py
inspire_schemas/countries/__init__.py
inspire_schemas/countries/iso_3166-1.json
inspire_schemas/countries/iso_3166-3.json
inspire_schemas/countries/iso_overrides.json
inspire_schemas/parsers/__init__.py
inspire_schemas/parsers/arxiv.py
inspire_schemas/parsers/author_xml.py
inspire_schemas/parsers/crossref.py
inspire_schemas/parsers/elsevier.py
inspire_schemas/parsers/hepdata.py
inspire_schemas/parsers/jats.py
inspire_schemas/parsers/utils.py
inspire_schemas/readers/__init__.py
inspire_schemas/readers/conference.py
inspire_schemas/readers/literature.py
inspire_schemas/records/__init__.py
inspire_schemas/records/authors.json
inspire_schemas/records/conferences.json
inspire_schemas/records/data.json
inspire_schemas/records/experiments.json
inspire_schemas/records/hep.json
inspire_schemas/records/institutions.json
inspire_schemas/records/jobs.json
inspire_schemas/records/journals.json
inspire_schemas/records/seminars.json
inspire_schemas/records/elements/__init__.py
inspire_schemas/records/elements/acquisition_source.json
inspire_schemas/records/elements/address.json
inspire_schemas/records/elements/arxiv_categories.json
inspire_schemas/records/elements/cnum.json
inspire_schemas/records/elements/contact.json
inspire_schemas/records/elements/country_code.json
inspire_schemas/records/elements/degree_type.json
inspire_schemas/records/elements/document_type.json
inspire_schemas/records/elements/id.json
inspire_schemas/records/elements/inspire_experiment_classification.json
inspire_schemas-61.6.27.dist-info/licenses/LICENSE
inspire_schemas-61.6.27.dist-info/METADATA
inspire_schemas-61.6.27.dist-info/WHEEL
inspire_schemas-61.6.27.dist-info/top_level.txt
inspire_schemas-61.6.27.dist-info/RECORD
